{
  "trucks": 15,
  "trucksCapacity": 1544,
  "warehouse": { "x": 0.0, "y": 0.0 },
  "customers": [

    {
      "id": 1,
      "d": 122,
      "x": -11.0,
      "y": 106.0
    },
    {
      "id": 2,
      "d": 30,
      "x": -12.0,
      "y": 115.0
    },
    {
      "id": 3,
      "d": 3,
      "x": 4.0,
      "y": 123.0
    },
    {
      "id": 4,
      "d": 5,
      "x": 7.0,
      "y": 113.0
    },
    {
      "id": 5,
      "d": 422,
      "x": -13.0,
      "y": 125.0
    },
    {
      "id": 6,
      "d": 13,
      "x": -11.0,
      "y": 105.0
    },
    {
      "id": 7,
      "d": 22,
      "x": 8.0,
      "y": 107.0
    },
    {
      "id": 8,
      "d": 173,
      "x": 6.0,
      "y": 111.0
    },
    {
      "id": 9,
      "d": 41,
      "x": 0.0,
      "y": 125.0
    },
    {
      "id": 10,
      "d": 8,
      "x": 8.0,
      "y": 118.0
    },
    {
      "id": 11,
      "d": 8,
      "x": 4.0,
      "y": 114.0
    },
    {
      "id": 12,
      "d": 110,
      "x": 0.0,
      "y": 113.0
    },
    {
      "id": 13,
      "d": 198,
      "x": -5.0,
      "y": 109.0
    },
    {
      "id": 14,
      "d": 384,
      "x": -11.0,
      "y": 112.0
    },
    {
      "id": 15,
      "d": 193,
      "x": 6.0,
      "y": 106.0
    },
    {
      "id": 16,
      "d": 238,
      "x": -11.0,
      "y": 123.0
    },
    {
      "id": 17,
      "d": 265,
      "x": -6.0,
      "y": 126.0
    },
    {
      "id": 18,
      "d": 3,
      "x": 26.0,
      "y": -33.0
    },
    {
      "id": 19,
      "d": 469,
      "x": 34.0,
      "y": -38.0
    },
    {
      "id": 20,
      "d": 7,
      "x": 26.0,
      "y": -44.0
    },
    {
      "id": 21,
      "d": 6,
      "x": 28.0,
      "y": -36.0
    },
    {
      "id": 22,
      "d": 108,
      "x": 30.0,
      "y": -39.0
    },
    {
      "id": 23,
      "d": 10,
      "x": 44.0,
      "y": -31.0
    },
    {
      "id": 24,
      "d": 40,
      "x": 43.0,
      "y": -27.0
    },
    {
      "id": 25,
      "d": 635,
      "x": 45.0,
      "y": -22.0
    },
    {
      "id": 26,
      "d": 49,
      "x": 37.0,
      "y": -44.0
    },
    {
      "id": 27,
      "d": 149,
      "x": 32.0,
      "y": -23.0
    },
    {
      "id": 28,
      "d": 403,
      "x": 35.0,
      "y": -41.0
    },
    {
      "id": 29,
      "d": 42,
      "x": 48.0,
      "y": -27.0
    },
    {
      "id": 30,
      "d": 70,
      "x": 41.0,
      "y": -35.0
    },
    {
      "id": 31,
      "d": 201,
      "x": 45.0,
      "y": -41.0
    },
    {
      "id": 32,
      "d": 66,
      "x": 43.0,
      "y": -36.0
    },
    {
      "id": 33,
      "d": 526,
      "x": 34.0,
      "y": -38.0
    },
    {
      "id": 34,
      "d": 6,
      "x": 43.0,
      "y": -23.0
    },
    {
      "id": 35,
      "d": 279,
      "x": 32.0,
      "y": -41.0
    },
    {
      "id": 36,
      "d": 160,
      "x": 33.0,
      "y": -24.0
    },
    {
      "id": 37,
      "d": 3,
      "x": 48.0,
      "y": -26.0
    },
    {
      "id": 38,
      "d": 4,
      "x": 102.0,
      "y": 85.0
    },
    {
      "id": 39,
      "d": 105,
      "x": 90.0,
      "y": 69.0
    },
    {
      "id": 40,
      "d": 46,
      "x": 95.0,
      "y": 88.0
    },
    {
      "id": 41,
      "d": 474,
      "x": 79.0,
      "y": 74.0
    },
    {
      "id": 42,
      "d": 7,
      "x": 77.0,
      "y": 89.0
    },
    {
      "id": 43,
      "d": 7,
      "x": 99.0,
      "y": 81.0
    },
    {
      "id": 44,
      "d": 99,
      "x": 99.0,
      "y": 80.0
    },
    {
      "id": 45,
      "d": 126,
      "x": 81.0,
      "y": 84.0
    },
    {
      "id": 46,
      "d": 119,
      "x": 77.0,
      "y": 69.0
    },
    {
      "id": 47,
      "d": 46,
      "x": 86.0,
      "y": 85.0
    },
    {
      "id": 48,
      "d": 273,
      "x": 82.0,
      "y": 89.0
    },
    {
      "id": 49,
      "d": 91,
      "x": 86.0,
      "y": 86.0
    },
    {
      "id": 50,
      "d": 294,
      "x": 84.0,
      "y": 87.0
    },
    {
      "id": 51,
      "d": 4,
      "x": 23.0,
      "y": 14.0
    },
    {
      "id": 52,
      "d": 81,
      "x": 13.0,
      "y": 4.0
    },
    {
      "id": 53,
      "d": 285,
      "x": 13.0,
      "y": 7.0
    },
    {
      "id": 54,
      "d": 90,
      "x": 16.0,
      "y": 2.0
    },
    {
      "id": 55,
      "d": 462,
      "x": 17.0,
      "y": -1.0
    },
    {
      "id": 56,
      "d": 65,
      "x": 16.0,
      "y": 3.0
    },
    {
      "id": 57,
      "d": 6,
      "x": 13.0,
      "y": 10.0
    },
    {
      "id": 58,
      "d": 4,
      "x": 23.0,
      "y": 11.0
    },
    {
      "id": 59,
      "d": 529,
      "x": 15.0,
      "y": 5.0
    },
    {
      "id": 60,
      "d": 165,
      "x": 17.0,
      "y": -1.0
    },
    {
      "id": 61,
      "d": 4,
      "x": 11.0,
      "y": 0.0
    },
    {
      "id": 62,
      "d": 394,
      "x": 19.0,
      "y": 1.0
    },
    {
      "id": 63,
      "d": 3,
      "x": 14.0,
      "y": 3.0
    },
    {
      "id": 64,
      "d": 60,
      "x": 18.0,
      "y": -3.0
    },
    {
      "id": 65,
      "d": 899,
      "x": 118.0,
      "y": 8.0
    },
    {
      "id": 66,
      "d": 169,
      "x": 99.0,
      "y": 21.0
    },
    {
      "id": 67,
      "d": 10,
      "x": 106.0,
      "y": -5.0
    },
    {
      "id": 68,
      "d": 47,
      "x": 124.0,
      "y": 8.0
    },
    {
      "id": 69,
      "d": 37,
      "x": 104.0,
      "y": 3.0
    },
    {
      "id": 70,
      "d": 23,
      "x": 126.0,
      "y": 4.0
    },
    {
      "id": 71,
      "d": 25,
      "x": 115.0,
      "y": 7.0
    },
    {
      "id": 72,
      "d": 444,
      "x": 110.0,
      "y": -3.0
    },
    {
      "id": 73,
      "d": 3,
      "x": 98.0,
      "y": -6.0
    },
    {
      "id": 74,
      "d": 99,
      "x": 111.0,
      "y": 13.0
    },
    {
      "id": 75,
      "d": 58,
      "x": -67.0,
      "y": 90.0
    },
    {
      "id": 76,
      "d": 7,
      "x": -56.0,
      "y": 96.0
    },
    {
      "id": 77,
      "d": 11,
      "x": -56.0,
      "y": 97.0
    },
    {
      "id": 78,
      "d": 15,
      "x": -57.0,
      "y": 100.0
    },
    {
      "id": 79,
      "d": 381,
      "x": -54.0,
      "y": 101.0
    },
    {
      "id": 80,
      "d": 7,
      "x": -50.0,
      "y": 96.0
    },
    {
      "id": 81,
      "d": 39,
      "x": -64.0,
      "y": 103.0
    },
    {
      "id": 82,
      "d": 502,
      "x": -63.0,
      "y": 103.0
    },
    {
      "id": 83,
      "d": 115,
      "x": -57.0,
      "y": 100.0
    },
    {
      "id": 84,
      "d": 85,
      "x": -53.0,
      "y": 106.0
    },
    {
      "id": 85,
      "d": 3,
      "x": -57.0,
      "y": 96.0
    },
    {
      "id": 86,
      "d": 136,
      "x": -67.0,
      "y": 97.0
    },
    {
      "id": 87,
      "d": 111,
      "x": -61.0,
      "y": 98.0
    },
    {
      "id": 88,
      "d": 66,
      "x": -66.0,
      "y": 95.0
    },
    {
      "id": 89,
      "d": 50,
      "x": -51.0,
      "y": 104.0
    },
    {
      "id": 90,
      "d": 252,
      "x": -62.0,
      "y": 95.0
    },
    {
      "id": 91,
      "d": 4,
      "x": -67.0,
      "y": 106.0
    },
    {
      "id": 92,
      "d": 119,
      "x": -51.0,
      "y": 102.0
    },
    {
      "id": 93,
      "d": 746,
      "x": -86.0,
      "y": 87.0
    },
    {
      "id": 94,
      "d": 6,
      "x": -82.0,
      "y": 78.0
    },
    {
      "id": 95,
      "d": 51,
      "x": -92.0,
      "y": 86.0
    },
    {
      "id": 96,
      "d": 322,
      "x": -86.0,
      "y": 78.0
    },
    {
      "id": 97,
      "d": 1023,
      "x": 6.0,
      "y": 67.0
    },
    {
      "id": 98,
      "d": 5,
      "x": 13.0,
      "y": 59.0
    },
    {
      "id": 99,
      "d": 10,
      "x": 21.0,
      "y": 66.0
    },
    {
      "id": 100,
      "d": 153,
      "x": 8.0,
      "y": 59.0
    },
    {
      "id": 101,
      "d": 29,
      "x": 20.0,
      "y": 70.0
    },
    {
      "id": 102,
      "d": 13,
      "x": 1.0,
      "y": 62.0
    },
    {
      "id": 103,
      "d": 3,
      "x": 19.0,
      "y": 57.0
    },
    {
      "id": 104,
      "d": 4,
      "x": 15.0,
      "y": 70.0
    },
    {
      "id": 105,
      "d": 70,
      "x": 20.0,
      "y": 55.0
    },
    {
      "id": 106,
      "d": 9,
      "x": 8.0,
      "y": 51.0
    },
    {
      "id": 107,
      "d": 147,
      "x": 3.0,
      "y": 54.0
    },
    {
      "id": 108,
      "d": 3,
      "x": 18.0,
      "y": 68.0
    },
    {
      "id": 109,
      "d": 10,
      "x": 12.0,
      "y": 53.0
    },
    {
      "id": 110,
      "d": 4,
      "x": 3.0,
      "y": 65.0
    },
    {
      "id": 111,
      "d": 439,
      "x": 4.0,
      "y": 62.0
    },
    {
      "id": 112,
      "d": 14,
      "x": 19.0,
      "y": 52.0
    },
    {
      "id": 113,
      "d": 729,
      "x": 92.0,
      "y": -28.0
    },
    {
      "id": 114,
      "d": 29,
      "x": 92.0,
      "y": -26.0
    },
    {
      "id": 115,
      "d": 3,
      "x": 80.0,
      "y": -28.0
    },
    {
      "id": 116,
      "d": 98,
      "x": 91.0,
      "y": -18.0
    },
    {
      "id": 117,
      "d": 113,
      "x": 93.0,
      "y": -24.0
    },
    {
      "id": 118,
      "d": 122,
      "x": 76.0,
      "y": -15.0
    },
    {
      "id": 119,
      "d": 11,
      "x": 88.0,
      "y": -33.0
    },
    {
      "id": 120,
      "d": 90,
      "x": 83.0,
      "y": -28.0
    },
    {
      "id": 121,
      "d": 789,
      "x": 86.0,
      "y": -23.0
    },
    {
      "id": 122,
      "d": 6,
      "x": 92.0,
      "y": -20.0
    },
    {
      "id": 123,
      "d": 179,
      "x": 82.0,
      "y": -29.0
    },
    {
      "id": 124,
      "d": 3,
      "x": 88.0,
      "y": -29.0
    },
    {
      "id": 125,
      "d": 3,
      "x": 82.0,
      "y": -27.0
    },
    {
      "id": 126,
      "d": 21,
      "x": 88.0,
      "y": -13.0
    },
    {
      "id": 127,
      "d": 869,
      "x": 83.0,
      "y": -29.0
    },
    {
      "id": 128,
      "d": 246,
      "x": 90.0,
      "y": -17.0
    },
    {
      "id": 129,
      "d": 10,
      "x": 49.0,
      "y": -4.0
    },
    {
      "id": 130,
      "d": 36,
      "x": 58.0,
      "y": -6.0
    },
    {
      "id": 131,
      "d": 14,
      "x": 64.0,
      "y": -7.0
    },
    {
      "id": 132,
      "d": 134,
      "x": 54.0,
      "y": -15.0
    },
    {
      "id": 133,
      "d": 175,
      "x": 66.0,
      "y": -3.0
    },
    {
      "id": 134,
      "d": 32,
      "x": 65.0,
      "y": -13.0
    },
    {
      "id": 135,
      "d": 20,
      "x": 57.0,
      "y": -20.0
    },
    {
      "id": 136,
      "d": 212,
      "x": 38.0,
      "y": -2.0
    },
    {
      "id": 137,
      "d": 45,
      "x": -44.0,
      "y": 88.0
    },
    {
      "id": 138,
      "d": 173,
      "x": -36.0,
      "y": 100.0
    },
    {
      "id": 139,
      "d": 240,
      "x": -37.0,
      "y": 98.0
    },
    {
      "id": 140,
      "d": 16,
      "x": -39.0,
      "y": 110.0
    },
    {
      "id": 141,
      "d": 27,
      "x": -34.0,
      "y": 111.0
    },
    {
      "id": 142,
      "d": 61,
      "x": -47.0,
      "y": 111.0
    },
    {
      "id": 143,
      "d": 203,
      "x": -28.0,
      "y": 105.0
    },
    {
      "id": 144,
      "d": 5,
      "x": -38.0,
      "y": 98.0
    },
    {
      "id": 145,
      "d": 369,
      "x": -32.0,
      "y": 91.0
    },
    {
      "id": 146,
      "d": 81,
      "x": -25.0,
      "y": 97.0
    },
    {
      "id": 147,
      "d": 128,
      "x": -46.0,
      "y": 111.0
    },
    {
      "id": 148,
      "d": 406,
      "x": -36.0,
      "y": 107.0
    },
    {
      "id": 149,
      "d": 32,
      "x": -35.0,
      "y": 92.0
    },
    {
      "id": 150,
      "d": 13,
      "x": -4.0,
      "y": 106.0
    }
  ]
}